latex_tools/__init__.py
latex_tools/latex_tools.py
latex_builder_test_project-0.1.1.dist-info/METADATA
latex_builder_test_project-0.1.1.dist-info/WHEEL
latex_builder_test_project-0.1.1.dist-info/RECORD
